kspl/__init__.py
kspl/_run.py
kspl/config_slurper.py
kspl/edit.py
kspl/generate.py
kspl/gui.py
kspl/gui_cmd.py
kspl/kconfig.py
kspl/main.py
kspl/py.typed
kspl-1.9.0.dist-info/METADATA
kspl-1.9.0.dist-info/WHEEL
kspl-1.9.0.dist-info/entry_points.txt
kspl-1.9.0.dist-info/licenses/LICENSE
kspl-1.9.0.dist-info/RECORD
