Metadata-Version: 2.4
Name: kspl
Version: 1.9.0
Summary: KConfig GUI for Software Product Lines with multiple variants.
License: MIT
License-File: LICENSE
Author: Cuinixam
Author-email: cuinixam@me.com
Requires-Python: <4.0,>=3.10
Classifier: Development Status :: 2 - Pre-Alpha
Classifier: Intended Audience :: Developers
Classifier: Natural Language :: English
Classifier: Operating System :: OS Independent
Classifier: Programming Language :: Python :: 3 :: Only
Classifier: Programming Language :: Python :: 3.10
Classifier: Programming Language :: Python :: 3.11
Classifier: Programming Language :: Python :: 3.12
Classifier: Programming Language :: Python :: 3.13
Classifier: Topic :: Software Development :: Libraries
Requires-Dist: CTkToolTip (>=0.8,<1)
Requires-Dist: customtkinter (>=5,<6)
Requires-Dist: kconfiglib (>=14,<15)
Requires-Dist: py-app-dev (>=2,<3)
Project-URL: Bug Tracker, https://github.com/cuinixam/kspl/issues
Project-URL: Changelog, https://github.com/cuinixam/kspl/blob/main/CHANGELOG.md
Project-URL: Repository, https://github.com/cuinixam/kspl
